xls_aws_sso_cli/__init__.py
xls_aws_sso_cli/auth.py
xls_aws_sso_cli/cli.py
xls_aws_sso_cli/pages/__init__.py
xls_aws_sso_cli/pages/home.py
xls_aws_sso_cli/pages/login.py
xls_aws_sso_cli-0.1.29.dist-info/METADATA
xls_aws_sso_cli-0.1.29.dist-info/WHEEL
xls_aws_sso_cli-0.1.29.dist-info/entry_points.txt
xls_aws_sso_cli-0.1.29.dist-info/top_level.txt
xls_aws_sso_cli-0.1.29.dist-info/RECORD
